ouseful_companydata/__init__.py
ouseful_companydata/companies_house.py
ouseful_companydata-0.0.1.dist-info/LICENSE
ouseful_companydata-0.0.1.dist-info/METADATA
ouseful_companydata-0.0.1.dist-info/WHEEL
ouseful_companydata-0.0.1.dist-info/top_level.txt
ouseful_companydata-0.0.1.dist-info/RECORD
